Workbook

Sheet Summary
A1: Quarterly operations
A4: Transactions | B4: =COUNTA(Transactions!A4:A203) -> 200
A5: Net total | B5: =SUM(Transactions!F4:F203) -> 16490
A6: Tax total | B6: =SUM(Transactions!G4:G203) -> 1236.95
A7: Gross total | B7: =SUM(Transactions!H4:H203) -> 17726.95
A8: North net | B8: =SUMIF(Transactions!C4:C203,"North",Transactions!F4:F203) -> 4133.75
A9: Reconciliation | B9: =ROUND(B5+B6-B7,2) -> 0
A10: Blank result | B10: =IF(B4>0,"",0)
A11: Handled input error | B11: =IFERROR('Inputs & notes'!B12,0) -> 0
A13: This synthetic workbook checks linked calculations, readable imported geometry, and export fidelity. The paragraph must remain completely visible across three merged rows. Final sentence: the complete paragraph is retained.
A17: Prepared by | D17: Reviewed by

Sheet Transactions
A1: Transaction detail
A3: Invoice | B3: Date | C3: Region | D3: Quantity | E3: Unit price | F3: Net | G3: Tax | H3: Gross
A4: INV-00001 | B4: 46023 | C4: North | D4: 7 | E4: 15 | F4: =D4*E4 -> 105 | G4: =ROUND(F4*'Inputs & notes'!$B$3,2) -> 7.88 | H4: =F4+G4 -> 112.88
A5: INV-00002 | B5: 46024 | C5: South | D5: 6 | E5: 16.25 | F5: =D5*E5 -> 97.5 | G5: =ROUND(F5*'Inputs & notes'!$B$3,2) -> 7.31 | H5: =F5+G5 -> 104.81
A6: INV-00003 | B6: 46025 | C6: East | D6: 7 | E6: 17.5 | F6: =D6*E6 -> 122.5 | G6: =ROUND(F6*'Inputs & notes'!$B$3,2) -> 9.19 | H6: =F6+G6 -> 131.69
A7: INV-00004 | B7: 46026 | C7: West | D7: 8 | E7: 10 | F7: =D7*E7 -> 80 | G7: =ROUND(F7*'Inputs & notes'!$B$3,2) -> 6 | H7: =F7+G7 -> 86
A8: INV-00005 | B8: 46027 | C8: North | D8: 9 | E8: 11.25 | F8: =D8*E8 -> 101.25 | G8: =ROUND(F8*'Inputs & notes'!$B$3,2) -> 7.59 | H8: =F8+G8 -> 108.84
A9: INV-00006 | B9: 46028 | C9: South | D9: 10 | E9: 12.5 | F9: =D9*E9 -> 125 | G9: =ROUND(F9*'Inputs & notes'!$B$3,2) -> 9.38 | H9: =F9+G9 -> 134.38
A10: INV-00007 | B10: 46029 | C10: East | D10: 11 | E10: 13.75 | F10: =D10*E10 -> 151.25 | G10: =ROUND(F10*'Inputs & notes'!$B$3,2) -> 11.34 | H10: =F10+G10 -> 162.59
A11: INV-00008 | B11: 46030 | C11: West | D11: 1 | E11: 15 | F11: =D11*E11 -> 15 | G11: =ROUND(F11*'Inputs & notes'!$B$3,2) -> 1.13 | H11: =F11+G11 -> 16.13
A12: INV-00009 | B12: 46031 | C12: North | D12: 2 | E12: 16.25 | F12: =D12*E12 -> 32.5 | G12: =ROUND(F12*'Inputs & notes'!$B$3,2) -> 2.44 | H12: =F12+G12 -> 34.94
A13: INV-00010 | B13: 46032 | C13: South | D13: 3 | E13: 17.5 | F13: =D13*E13 -> 52.5 | G13: =ROUND(F13*'Inputs & notes'!$B$3,2) -> 3.94 | H13: =F13+G13 -> 56.44
A14: INV-00011 | B14: 46033 | C14: East | D14: 4 | E14: 10 | F14: =D14*E14 -> 40 | G14: =ROUND(F14*'Inputs & notes'!$B$3,2) -> 3 | H14: =F14+G14 -> 43
A15: INV-00012 | B15: 46034 | C15: West | D15: 5 | E15: 11.25 | F15: =D15*E15 -> 56.25 | G15: =ROUND(F15*'Inputs & notes'!$B$3,2) -> 4.22 | H15: =F15+G15 -> 60.47
... A203: INV-00200 | B203: 46222 | C203: West | D203: 6 | E203: 10 | F203: =D203*E203 -> 60 | G203: =ROUND(F203*'Inputs & notes'!$B$3,2) -> 4.5 | H203: =F203+G203 -> 64.5

Sheet Inputs & notes
A1: Inputs and layout checks
A3: Tax rate | B3: 0.075
A5: Japanese | B5: 請求書と支払い — 日本語の確認
A6: Arabic | B6: فاتورة تجريبية باللغة العربية
A7: Accents | B7: Crème brûlée · é · €1.234,56 · 🧾
A9: Tight row | B9: 12345.67
A10: Top alignment | B10: 89012.34
A11: Identifier as text | B11: 00001234567890123456
A12: Native error cell | B12: #DIV/0!
A13: Boolean | B13: FALSE
A14: CSV quoting | B14: Comma, quote " and new line
A16: Long merged text with an explicit line break. The final line must remain inside the merged range when printing and exporting. Complete final line.

Sheet Audit hidden
A1: HIDDEN_AUDIT_SENTINEL | B1: =Summary!B9 -> 0
